db_in_json/__init__.py
db_in_json/files.py
db_in_json/main.py
db_in_json/queries.py
db_in_json-1.0.2.dist-info/LICENSE
db_in_json-1.0.2.dist-info/METADATA
db_in_json-1.0.2.dist-info/WHEEL
db_in_json-1.0.2.dist-info/top_level.txt
db_in_json-1.0.2.dist-info/RECORD
