Metadata-Version: 2.1
Name: db_in_json
Version: 1.0.2
Summary: A small json database
Author: BDN_fr
Project-URL: Homepage, https://github.com/BDN-fr/db_in_json
Project-URL: Issues, https://github.com/BDN-fr/db_in_json/issues
Classifier: Programming Language :: Python :: 3
Classifier: License :: OSI Approved :: MIT License
Classifier: Operating System :: OS Independent
Requires-Python: >=3.8
License-File: LICENSE
